hic_straw_ajg.cpython-313-darwin.so
hic_straw_ajg-1.0.2.data/data/hic_straw_ajg/straw.h
hic_straw_ajg-1.0.2.dist-info/licenses/LICENSE
hic_straw_ajg-1.0.2.dist-info/METADATA
hic_straw_ajg-1.0.2.dist-info/WHEEL
hic_straw_ajg-1.0.2.dist-info/top_level.txt
hic_straw_ajg-1.0.2.dist-info/RECORD
