Metadata-Version: 2.4
Name: hic_straw_ajg
Version: 1.0.2
Summary: Straw bound with pybind11 from hic-straw 1.3.1
Home-page: https://github.com/ajgouhier/hic_straw_ajg
Author: Arthur Gouhier
Author-email: ajgouhier@gmail.com
License: MIT
Requires-Python: >3.3
License-File: LICENSE
Requires-Dist: numpy
Requires-Dist: pybind11>=2.4
Dynamic: author
Dynamic: author-email
Dynamic: description
Dynamic: description-content-type
Dynamic: home-page
Dynamic: license
Dynamic: license-file
Dynamic: requires-dist
Dynamic: requires-python
Dynamic: summary
